<?xml version="1.0" encoding="UTF-8"?><scenario name="CCSP450">
	<world>
		<region name="USA">
			<ghgpolicy name="CO2_LTG">
				<market>global</market>
                <fixedTax year="2025">25</fixedTax>
                <fixedTax year="2030">31.9070390625</fixedTax>
                <fixedTax year="2035">40.722365669436</fixedTax>
                <fixedTax year="2040">51.9732044852842</fixedTax>
                <fixedTax year="2045">66.3324426286105</fixedTax>
                <fixedTax year="2050">84.6588735224847</fixedTax>
                <fixedTax year="2055">108.048559378767</fixedTax>
                <fixedTax year="2060">137.900384189806</fixedTax>
                <fixedTax year="2065">175.999717803116</fixedTax>
                <fixedTax year="2070">224.62519483732</fixedTax>
                <fixedTax year="2075">286.684994643842</fixedTax>
                <fixedTax year="2080">365.890772909347</fixedTax>
                <fixedTax year="2085">466.979647353074</fixedTax>
                <fixedTax year="2090">595.997513979481</fixedTax>
                <fixedTax year="2095">760.660638387847</fixedTax>
                <fixedTax year="2100">970.817148093889</fixedTax>
			</ghgpolicy>
		</region>
		<region name="Canada">
			<ghgpolicy name="CO2_LTG">
				<market>global</market>
			</ghgpolicy>
		</region>
		<region name="EU-15">
			<ghgpolicy name="CO2_LTG">
				<market>global</market>
			</ghgpolicy>
		</region>
        <region name="Europe_Non_EU">
			<ghgpolicy name="CO2_LTG">
				<market>global</market>
			</ghgpolicy>
		</region>
        <region name="European Free Trade Association">
			<ghgpolicy name="CO2_LTG">
				<market>global</market>
			</ghgpolicy>
		</region>
		<region name="Japan">
			<ghgpolicy name="CO2_LTG">
				<market>global</market>
			</ghgpolicy>
		</region>
		<region name="Australia_NZ">
			<ghgpolicy name="CO2_LTG">
				<market>global</market>
			</ghgpolicy>
		</region>
		<region name="Central Asia">
			<ghgpolicy name="CO2_LTG">
				<market>global</market>
			</ghgpolicy>
		</region>
        <region name="Russia">
			<ghgpolicy name="CO2_LTG">
				<market>global</market>
			</ghgpolicy>
		</region>
		<region name="China">
			<ghgpolicy name="CO2_LTG">
				<market>global</market>
			</ghgpolicy>
		</region>
		<region name="Middle East">
			<ghgpolicy name="CO2_LTG">
				<market>global</market>
			</ghgpolicy>
		</region>
		<region name="Africa_Eastern">
			<ghgpolicy name="CO2_LTG">
				<market>global</market>
			</ghgpolicy>
		</region>
        <region name="Africa_Northern">
			<ghgpolicy name="CO2_LTG">
				<market>global</market>
			</ghgpolicy>
		</region>
        <region name="Africa_Southern">
			<ghgpolicy name="CO2_LTG">
				<market>global</market>
			</ghgpolicy>
		</region>
        <region name="Africa_Western">
			<ghgpolicy name="CO2_LTG">
				<market>global</market>
			</ghgpolicy>
		</region>
        <region name="South Africa">
			<ghgpolicy name="CO2_LTG">
				<market>global</market>
			</ghgpolicy>
		</region>
		<region name="Brazil">
			<ghgpolicy name="CO2_LTG">
				<market>global</market>
			</ghgpolicy>
		</region>
        <region name="Central America and Caribbean">
			<ghgpolicy name="CO2_LTG">
				<market>global</market>
			</ghgpolicy>
		</region>
        <region name="Mexico">
			<ghgpolicy name="CO2_LTG">
				<market>global</market>
			</ghgpolicy>
		</region>
        <region name="South America_Northern">
			<ghgpolicy name="CO2_LTG">
				<market>global</market>
			</ghgpolicy>
		</region>
        <region name="South America_Southern">
			<ghgpolicy name="CO2_LTG">
				<market>global</market>
			</ghgpolicy>
		</region>
        <region name="Argentina">
			<ghgpolicy name="CO2_LTG">
				<market>global</market>
			</ghgpolicy>
		</region>
        <region name="Colombia">
			<ghgpolicy name="CO2_LTG">
				<market>global</market>
			</ghgpolicy>
		</region>
		<region name="Indonesia">
			<ghgpolicy name="CO2_LTG">
				<market>global</market>
			</ghgpolicy>
		</region>
        <region name="Pakistan">
			<ghgpolicy name="CO2_LTG">
				<market>global</market>
			</ghgpolicy>
		</region>
        <region name="South Asia">
			<ghgpolicy name="CO2_LTG">
				<market>global</market>
			</ghgpolicy>
		</region>
        <region name="Southeast Asia">
			<ghgpolicy name="CO2_LTG">
				<market>global</market>
			</ghgpolicy>
		</region>
        <region name="Taiwan">
			<ghgpolicy name="CO2_LTG">
				<market>global</market>
			</ghgpolicy>
		</region>
		<region name="Europe_Eastern">
			<ghgpolicy name="CO2_LTG">
				<market>global</market>
			</ghgpolicy>
		</region>
        <region name="EU-12">
			<ghgpolicy name="CO2_LTG">
				<market>global</market>
			</ghgpolicy>
		</region>
		<region name="South Korea">
			<ghgpolicy name="CO2_LTG">
				<market>global</market>
			</ghgpolicy>
		</region>
		<region name="India">
			<ghgpolicy name="CO2_LTG">
				<market>global</market>
			</ghgpolicy>
		</region>
	</world>
</scenario>
