<?xml version="1.0" encoding="UTF-8"?>
<scenario>
   <world>
      <region name="USA">
         <supplysector name="cement">
            <subsector name="cement (conv)">
               <technology name="cement (conv)">
                  <period year="1975">
                     <minicam-energy-input name="limestone">
                        <coefficient>1.496</coefficient>
                     </minicam-energy-input>
                     <minicam-energy-input name="process heat cement">
                        <coefficient>3.964</coefficient>
                     </minicam-energy-input>
                     <minicam-energy-input name="elect_td_ind">
                        <coefficient>0.529</coefficient>
                     </minicam-energy-input>
                  </period>
                  <period year="1990">
                     <minicam-energy-input name="limestone">
                        <coefficient>1.496</coefficient>
                     </minicam-energy-input>
                     <minicam-energy-input name="process heat cement">
                        <coefficient>3.964</coefficient>
                     </minicam-energy-input>
                     <minicam-energy-input name="elect_td_ind">
                        <coefficient>0.529</coefficient>
                     </minicam-energy-input>
                  </period>
                  <period year="2005">
                     <minicam-energy-input name="limestone">
                        <coefficient>1.496</coefficient>
                     </minicam-energy-input>
                     <minicam-energy-input name="process heat cement">
                        <coefficient>3.951</coefficient>
                     </minicam-energy-input>
                     <minicam-energy-input name="elect_td_ind">
                        <coefficient>0.515</coefficient>
                     </minicam-energy-input>
                  </period>
                  <period year="2020">
                     <minicam-energy-input name="limestone">
                        <coefficient>1.496</coefficient>
                     </minicam-energy-input>
                     <minicam-energy-input name="process heat cement">
                        <coefficient>3.806</coefficient>
                     </minicam-energy-input>
                     <minicam-energy-input name="elect_td_ind">
                        <coefficient>0.496</coefficient>
                     </minicam-energy-input>
                  </period>
                  <period year="2035">
                     <minicam-energy-input name="limestone">
                        <coefficient>1.496</coefficient>
                     </minicam-energy-input>
                     <minicam-energy-input name="process heat cement">
                        <coefficient>3.666</coefficient>
                     </minicam-energy-input>
                     <minicam-energy-input name="elect_td_ind">
                        <coefficient>0.478</coefficient>
                     </minicam-energy-input>
                  </period>
                  <period year="2050">
                     <minicam-energy-input name="limestone">
                        <coefficient>1.441</coefficient>
                     </minicam-energy-input>
                     <minicam-energy-input name="process heat cement">
                        <coefficient>3.531</coefficient>
                     </minicam-energy-input>
                     <minicam-energy-input name="elect_td_ind">
                        <coefficient>0.460</coefficient>
                     </minicam-energy-input>
                  </period>
                  <period year="2065">
                     <minicam-energy-input name="limestone">
                        <coefficient>1.388</coefficient>
                     </minicam-energy-input>
                     <minicam-energy-input name="process heat cement">
                        <coefficient>3.400</coefficient>
                     </minicam-energy-input>
                     <minicam-energy-input name="elect_td_ind">
                        <coefficient>0.443</coefficient>
                     </minicam-energy-input>
                  </period>
                  <period year="2080">
                     <minicam-energy-input name="limestone">
                        <coefficient>1.337</coefficient>
                     </minicam-energy-input>
                     <minicam-energy-input name="process heat cement">
                        <coefficient>3.275</coefficient>
                     </minicam-energy-input>
                     <minicam-energy-input name="elect_td_ind">
                        <coefficient>0.427</coefficient>
                     </minicam-energy-input>
                  </period>
                  <period year="2095">
                     <minicam-energy-input name="limestone">
                        <coefficient>1.287</coefficient>
                     </minicam-energy-input>
                     <minicam-energy-input name="process heat cement">
                        <coefficient>3.154</coefficient>
                     </minicam-energy-input>
                     <minicam-energy-input name="elect_td_ind">
                        <coefficient>0.411</coefficient>
                     </minicam-energy-input>
                  </period>
               </technology>
            </subsector>
            <subsector name="cement_CCS">
               <technology name="cement_CCS">
                  <period year="1975">
                     <minicam-energy-input name="limestone">
                        <coefficient>1.496</coefficient>
                     </minicam-energy-input>
                     <minicam-energy-input name="process heat cement">
                        <coefficient>3.964</coefficient>
                     </minicam-energy-input>
                     <minicam-energy-input name="elect_td_ind">
                        <coefficient>0.529</coefficient>
                     </minicam-energy-input>
                  </period>
                  <period year="1990">
                     <minicam-energy-input name="limestone">
                        <coefficient>1.496</coefficient>
                     </minicam-energy-input>
                     <minicam-energy-input name="process heat cement">
                        <coefficient>3.964</coefficient>
                     </minicam-energy-input>
                     <minicam-energy-input name="elect_td_ind">
                        <coefficient>0.529</coefficient>
                     </minicam-energy-input>
                  </period>
                  <period year="2005">
                     <minicam-energy-input name="limestone">
                        <coefficient>1.496</coefficient>
                     </minicam-energy-input>
                     <minicam-energy-input name="process heat cement">
                        <coefficient>3.951</coefficient>
                     </minicam-energy-input>
                     <minicam-energy-input name="elect_td_ind">
                        <coefficient>0.515</coefficient>
                     </minicam-energy-input>
                  </period>
                  <period year="2020">
                     <minicam-energy-input name="limestone">
                        <coefficient>1.496</coefficient>
                     </minicam-energy-input>
                     <minicam-energy-input name="process heat cement">
                        <coefficient>3.806</coefficient>
                     </minicam-energy-input>
                     <minicam-energy-input name="elect_td_ind">
                        <coefficient>0.496</coefficient>
                     </minicam-energy-input>
                  </period>
                  <period year="2035">
                     <minicam-energy-input name="limestone">
                        <coefficient>1.496</coefficient>
                     </minicam-energy-input>
                     <minicam-energy-input name="process heat cement">
                        <coefficient>3.666</coefficient>
                     </minicam-energy-input>
                     <minicam-energy-input name="elect_td_ind">
                        <coefficient>0.478</coefficient>
                     </minicam-energy-input>
                  </period>
                  <period year="2050">
                     <minicam-energy-input name="limestone">
                        <coefficient>1.441</coefficient>
                     </minicam-energy-input>
                     <minicam-energy-input name="process heat cement">
                        <coefficient>3.531</coefficient>
                     </minicam-energy-input>
                     <minicam-energy-input name="elect_td_ind">
                        <coefficient>0.460</coefficient>
                     </minicam-energy-input>
                  </period>
                  <period year="2065">
                     <minicam-energy-input name="limestone">
                        <coefficient>1.388</coefficient>
                     </minicam-energy-input>
                     <minicam-energy-input name="process heat cement">
                        <coefficient>3.400</coefficient>
                     </minicam-energy-input>
                     <minicam-energy-input name="elect_td_ind">
                        <coefficient>0.443</coefficient>
                     </minicam-energy-input>
                  </period>
                  <period year="2080">
                     <minicam-energy-input name="limestone">
                        <coefficient>1.337</coefficient>
                     </minicam-energy-input>
                     <minicam-energy-input name="process heat cement">
                        <coefficient>3.275</coefficient>
                     </minicam-energy-input>
                     <minicam-energy-input name="elect_td_ind">
                        <coefficient>0.427</coefficient>
                     </minicam-energy-input>
                  </period>
                  <period year="2095">
                     <minicam-energy-input name="limestone">
                        <coefficient>1.287</coefficient>
                     </minicam-energy-input>
                     <minicam-energy-input name="process heat cement">
                        <coefficient>3.154</coefficient>
                     </minicam-energy-input>
                     <minicam-energy-input name="elect_td_ind">
                        <coefficient>0.411</coefficient>
                     </minicam-energy-input>
                  </period>
               </technology>
            </subsector>
         </supplysector>
      </region>
   </world>
</scenario>
